{
    "num_instances": 300, 
    "solved_instances": 298, 
    "succ_running_time": 2459.503, 
    "total_running_time": 2544.85, 
    "avg_runtime_per_succ_problem": 8.2534, 
    "N": 10, 
    "lattice_version": "Schnorr", 
    "results": [
        {
            "slope": -0.045752, 
            "first_right_norm": 7.9373, 
            "instance": 12, 
            "beta": 33, 
            "beta_norm": 33, 
            "walltime": 0.889
        }, 
        {
            "slope": -0.043899, 
            "first_right_norm": 7.9373, 
            "instance": 1, 
            "beta": 36, 
            "beta_norm": 36, 
            "walltime": 1.433
        }, 
        {
            "slope": -0.043412, 
            "first_right_norm": 7.9373, 
            "instance": 10, 
            "beta": 38, 
            "beta_norm": 38, 
            "walltime": 1.962
        }, 
        {
            "slope": -0.042857, 
            "first_right_norm": 7.9373, 
            "instance": 11, 
            "beta": 42, 
            "beta_norm": 42, 
            "walltime": 3.051
        }, 
        {
            "slope": -0.042211, 
            "first_right_norm": 7.9373, 
            "instance": 8, 
            "beta": 43, 
            "beta_norm": 43, 
            "walltime": 3.178
        }, 
        {
            "slope": -0.043701, 
            "first_right_norm": 7.9373, 
            "instance": 6, 
            "beta": 41, 
            "beta_norm": 41, 
            "walltime": 3.509
        }, 
        {
            "slope": -0.04197, 
            "first_right_norm": 7.9373, 
            "instance": 9, 
            "beta": 44, 
            "beta_norm": 44, 
            "walltime": 3.651
        }, 
        {
            "slope": -0.045867, 
            "first_right_norm": 7.9373, 
            "instance": 17, 
            "beta": 33, 
            "beta_norm": 33, 
            "walltime": 0.776
        }, 
        {
            "slope": -0.04301, 
            "first_right_norm": 7.9373, 
            "instance": 18, 
            "beta": 42, 
            "beta_norm": 42, 
            "walltime": 2.788
        }, 
        {
            "slope": -0.041413, 
            "first_right_norm": 7.9373, 
            "instance": 13, 
            "beta": 46, 
            "beta_norm": 46, 
            "walltime": 5.9
        }, 
        {
            "slope": -0.042636, 
            "first_right_norm": 7.9373, 
            "instance": 19, 
            "beta": 44, 
            "beta_norm": 44, 
            "walltime": 3.493
        }, 
        {
            "slope": -0.042084, 
            "first_right_norm": 7.9373, 
            "instance": 2, 
            "beta": 49, 
            "beta_norm": 49, 
            "walltime": 9.263
        }, 
        {
            "slope": -0.042406, 
            "first_right_norm": 7.9373, 
            "instance": 3, 
            "beta": 50, 
            "beta_norm": 50, 
            "walltime": 10.866
        }, 
        {
            "slope": -0.041979, 
            "first_right_norm": 7.9373, 
            "instance": 22, 
            "beta": 43, 
            "beta_norm": 43, 
            "walltime": 3.12
        }, 
        {
            "slope": -0.041156, 
            "first_right_norm": 7.9373, 
            "instance": 7, 
            "beta": 51, 
            "beta_norm": 51, 
            "walltime": 11.606
        }, 
        {
            "slope": -0.043348, 
            "first_right_norm": 7.9373, 
            "instance": 26, 
            "beta": 36, 
            "beta_norm": 36, 
            "walltime": 1.363
        }, 
        {
            "slope": -0.042178, 
            "first_right_norm": 7.9373, 
            "instance": 14, 
            "beta": 51, 
            "beta_norm": 51, 
            "walltime": 11.943
        }, 
        {
            "slope": -0.041657, 
            "first_right_norm": 7.9373, 
            "instance": 5, 
            "beta": 53, 
            "beta_norm": 53, 
            "walltime": 14.76
        }, 
        {
            "slope": -0.04203, 
            "first_right_norm": 7.9373, 
            "instance": 16, 
            "beta": 50, 
            "beta_norm": 50, 
            "walltime": 11.032
        }, 
        {
            "slope": -0.041933, 
            "first_right_norm": 7.9373, 
            "instance": 15, 
            "beta": 51, 
            "beta_norm": 51, 
            "walltime": 12.48
        }, 
        {
            "slope": -0.042664, 
            "first_right_norm": 7.9373, 
            "instance": 27, 
            "beta": 44, 
            "beta_norm": 44, 
            "walltime": 3.424
        }, 
        {
            "slope": -0.043898, 
            "first_right_norm": 7.9373, 
            "instance": 28, 
            "beta": 38, 
            "beta_norm": 38, 
            "walltime": 2.227
        }, 
        {
            "slope": -0.041904, 
            "first_right_norm": 7.9373, 
            "instance": 4, 
            "beta": 53, 
            "beta_norm": 53, 
            "walltime": 16.76
        }, 
        {
            "slope": -0.043954, 
            "first_right_norm": 7.9373, 
            "instance": 29, 
            "beta": 39, 
            "beta_norm": 39, 
            "walltime": 2.328
        }, 
        {
            "slope": -0.042577, 
            "first_right_norm": 7.9373, 
            "instance": 31, 
            "beta": 40, 
            "beta_norm": 40, 
            "walltime": 2.519
        }, 
        {
            "slope": -0.042654, 
            "first_right_norm": 7.9373, 
            "instance": 32, 
            "beta": 42, 
            "beta_norm": 42, 
            "walltime": 2.985
        }, 
        {
            "slope": -0.042823, 
            "first_right_norm": 7.9373, 
            "instance": 25, 
            "beta": 48, 
            "beta_norm": 48, 
            "walltime": 8.08
        }, 
        {
            "slope": -0.042978, 
            "first_right_norm": 7.9373, 
            "instance": 30, 
            "beta": 45, 
            "beta_norm": 45, 
            "walltime": 4.803
        }, 
        {
            "slope": -0.043671, 
            "first_right_norm": 7.9373, 
            "instance": 38, 
            "beta": 37, 
            "beta_norm": 37, 
            "walltime": 1.771
        }, 
        {
            "slope": -0.04093, 
            "first_right_norm": 7.9373, 
            "instance": 23, 
            "beta": 52, 
            "beta_norm": 52, 
            "walltime": 13.503
        }, 
        {
            "slope": -0.041477, 
            "first_right_norm": 7.9373, 
            "instance": 34, 
            "beta": 46, 
            "beta_norm": 46, 
            "walltime": 5.37
        }, 
        {
            "slope": -0.041719, 
            "first_right_norm": 7.9373, 
            "instance": 20, 
            "beta": 54, 
            "beta_norm": 54, 
            "walltime": 18.01
        }, 
        {
            "slope": -0.043671, 
            "first_right_norm": 7.9373, 
            "instance": 40, 
            "beta": 39, 
            "beta_norm": 39, 
            "walltime": 2.412
        }, 
        {
            "slope": -0.043139, 
            "first_right_norm": 7.9373, 
            "instance": 43, 
            "beta": 37, 
            "beta_norm": 37, 
            "walltime": 1.827
        }, 
        {
            "slope": -0.041627, 
            "first_right_norm": 7.9373, 
            "instance": 21, 
            "beta": 54, 
            "beta_norm": 54, 
            "walltime": 17.982
        }, 
        {
            "slope": -0.042331, 
            "first_right_norm": 7.9373, 
            "instance": 37, 
            "beta": 47, 
            "beta_norm": 47, 
            "walltime": 6.987
        }, 
        {
            "slope": -0.042805, 
            "first_right_norm": 7.9373, 
            "instance": 42, 
            "beta": 45, 
            "beta_norm": 45, 
            "walltime": 4.53
        }, 
        {
            "slope": -0.040678, 
            "first_right_norm": 7.9373, 
            "instance": 24, 
            "beta": 54, 
            "beta_norm": 54, 
            "walltime": 17.609
        }, 
        {
            "slope": -0.042039, 
            "first_right_norm": 7.9373, 
            "instance": 44, 
            "beta": 44, 
            "beta_norm": 44, 
            "walltime": 3.43
        }, 
        {
            "slope": -0.041502, 
            "first_right_norm": 7.9373, 
            "instance": 35, 
            "beta": 50, 
            "beta_norm": 50, 
            "walltime": 11.164
        }, 
        {
            "slope": -0.040991, 
            "first_right_norm": 7.9373, 
            "instance": 33, 
            "beta": 52, 
            "beta_norm": 52, 
            "walltime": 13.607
        }, 
        {
            "slope": -0.04376, 
            "first_right_norm": 7.9373, 
            "instance": 50, 
            "beta": 39, 
            "beta_norm": 39, 
            "walltime": 2.396
        }, 
        {
            "slope": -0.041809, 
            "first_right_norm": 7.9373, 
            "instance": 41, 
            "beta": 50, 
            "beta_norm": 50, 
            "walltime": 10.81
        }, 
        {
            "slope": -0.042539, 
            "first_right_norm": 7.9373, 
            "instance": 47, 
            "beta": 47, 
            "beta_norm": 47, 
            "walltime": 7.125
        }, 
        {
            "slope": -0.041796, 
            "first_right_norm": 7.9373, 
            "instance": 46, 
            "beta": 48, 
            "beta_norm": 48, 
            "walltime": 8.42
        }, 
        {
            "slope": -0.041125, 
            "first_right_norm": 7.9373, 
            "instance": 36, 
            "beta": 54, 
            "beta_norm": 54, 
            "walltime": 17.584
        }, 
        {
            "slope": -0.041538, 
            "first_right_norm": 7.9373, 
            "instance": 54, 
            "beta": 45, 
            "beta_norm": 45, 
            "walltime": 4.373
        }, 
        {
            "slope": -0.041553, 
            "first_right_norm": 7.9373, 
            "instance": 51, 
            "beta": 48, 
            "beta_norm": 48, 
            "walltime": 7.815
        }, 
        {
            "slope": -0.043686, 
            "first_right_norm": 7.9373, 
            "instance": 57, 
            "beta": 36, 
            "beta_norm": 36, 
            "walltime": 1.598
        }, 
        {
            "slope": -0.041527, 
            "first_right_norm": 7.9373, 
            "instance": 48, 
            "beta": 50, 
            "beta_norm": 50, 
            "walltime": 11.2
        }, 
        {
            "slope": -0.043629, 
            "first_right_norm": 7.9373, 
            "instance": 58, 
            "beta": 39, 
            "beta_norm": 39, 
            "walltime": 2.141
        }, 
        {
            "slope": -0.041745, 
            "first_right_norm": 7.9373, 
            "instance": 52, 
            "beta": 49, 
            "beta_norm": 49, 
            "walltime": 9.514
        }, 
        {
            "slope": -0.042288, 
            "first_right_norm": 7.9373, 
            "instance": 49, 
            "beta": 51, 
            "beta_norm": 51, 
            "walltime": 12.155
        }, 
        {
            "slope": -0.045878, 
            "first_right_norm": 7.9373, 
            "instance": 64, 
            "beta": 33, 
            "beta_norm": 33, 
            "walltime": 0.98
        }, 
        {
            "slope": -0.042999, 
            "first_right_norm": 7.9373, 
            "instance": 62, 
            "beta": 43, 
            "beta_norm": 43, 
            "walltime": 3.197
        }, 
        {
            "slope": -0.041758, 
            "first_right_norm": 7.9373, 
            "instance": 59, 
            "beta": 46, 
            "beta_norm": 46, 
            "walltime": 6.017
        }, 
        {
            "slope": -0.041927, 
            "first_right_norm": 7.9373, 
            "instance": 56, 
            "beta": 49, 
            "beta_norm": 49, 
            "walltime": 9.44
        }, 
        {
            "slope": -0.042381, 
            "first_right_norm": 7.9373, 
            "instance": 65, 
            "beta": 42, 
            "beta_norm": 42, 
            "walltime": 3.005
        }, 
        {
            "slope": -0.043297, 
            "first_right_norm": 7.9373, 
            "instance": 66, 
            "beta": 42, 
            "beta_norm": 42, 
            "walltime": 3.205
        }, 
        {
            "slope": -0.043583, 
            "first_right_norm": 7.9373, 
            "instance": 67, 
            "beta": 38, 
            "beta_norm": 38, 
            "walltime": 2.088
        }, 
        {
            "slope": -0.042109, 
            "first_right_norm": 7.9373, 
            "instance": 55, 
            "beta": 50, 
            "beta_norm": 50, 
            "walltime": 11.263
        }, 
        {
            "slope": -0.043842, 
            "first_right_norm": 7.9373, 
            "instance": 68, 
            "beta": 39, 
            "beta_norm": 39, 
            "walltime": 2.358
        }, 
        {
            "slope": -0.043714, 
            "first_right_norm": 7.9373, 
            "instance": 69, 
            "beta": 39, 
            "beta_norm": 39, 
            "walltime": 2.221
        }, 
        {
            "slope": -0.043309, 
            "first_right_norm": 7.9373, 
            "instance": 72, 
            "beta": 39, 
            "beta_norm": 39, 
            "walltime": 2.209
        }, 
        {
            "slope": -0.042965, 
            "first_right_norm": 7.9373, 
            "instance": 71, 
            "beta": 41, 
            "beta_norm": 41, 
            "walltime": 2.841
        }, 
        {
            "slope": -0.043349, 
            "first_right_norm": 7.9373, 
            "instance": 73, 
            "beta": 42, 
            "beta_norm": 42, 
            "walltime": 3.022
        }, 
        {
            "slope": -0.041979, 
            "first_right_norm": 7.9373, 
            "instance": 39, 
            "beta": 58, 
            "beta_norm": 58, 
            "walltime": 28.399
        }, 
        {
            "slope": -0.041978, 
            "first_right_norm": 7.9373, 
            "instance": 61, 
            "beta": 51, 
            "beta_norm": 51, 
            "walltime": 12.371
        }, 
        {
            "slope": -0.040936, 
            "first_right_norm": 7.9373, 
            "instance": 45, 
            "beta": 57, 
            "beta_norm": 57, 
            "walltime": 25.474
        }, 
        {
            "slope": -0.041244, 
            "first_right_norm": 7.9373, 
            "instance": 63, 
            "beta": 50, 
            "beta_norm": 50, 
            "walltime": 10.856
        }, 
        {
            "slope": -0.042247, 
            "first_right_norm": 7.9373, 
            "instance": 79, 
            "beta": 40, 
            "beta_norm": 40, 
            "walltime": 2.565
        }, 
        {
            "slope": -0.042556, 
            "first_right_norm": 7.9373, 
            "instance": 75, 
            "beta": 46, 
            "beta_norm": 46, 
            "walltime": 5.817
        }, 
        {
            "slope": -0.04209, 
            "first_right_norm": 7.9373, 
            "instance": 70, 
            "beta": 48, 
            "beta_norm": 48, 
            "walltime": 8.289
        }, 
        {
            "slope": -0.041842, 
            "first_right_norm": 7.9373, 
            "instance": 74, 
            "beta": 47, 
            "beta_norm": 47, 
            "walltime": 7.293
        }, 
        {
            "slope": -0.043493, 
            "first_right_norm": 7.9373, 
            "instance": 81, 
            "beta": 44, 
            "beta_norm": 44, 
            "walltime": 3.48
        }, 
        {
            "slope": -0.041998, 
            "first_right_norm": 7.9373, 
            "instance": 53, 
            "beta": 57, 
            "beta_norm": 57, 
            "walltime": 23.562
        }, 
        {
            "slope": -0.041852, 
            "first_right_norm": 7.9373, 
            "instance": 76, 
            "beta": 46, 
            "beta_norm": 46, 
            "walltime": 6.014
        }, 
        {
            "slope": -0.041821, 
            "first_right_norm": 7.9373, 
            "instance": 60, 
            "beta": 54, 
            "beta_norm": 54, 
            "walltime": 18.492
        }, 
        {
            "slope": -0.04371, 
            "first_right_norm": 7.9373, 
            "instance": 84, 
            "beta": 37, 
            "beta_norm": 37, 
            "walltime": 1.784
        }, 
        {
            "slope": -0.041369, 
            "first_right_norm": 7.9373, 
            "instance": 77, 
            "beta": 47, 
            "beta_norm": 47, 
            "walltime": 7.278
        }, 
        {
            "slope": -0.04283, 
            "first_right_norm": 7.9373, 
            "instance": 82, 
            "beta": 46, 
            "beta_norm": 46, 
            "walltime": 6.229
        }, 
        {
            "slope": -0.043824, 
            "first_right_norm": 7.9373, 
            "instance": 87, 
            "beta": 40, 
            "beta_norm": 40, 
            "walltime": 2.699
        }, 
        {
            "slope": -0.042734, 
            "first_right_norm": 7.9373, 
            "instance": 85, 
            "beta": 47, 
            "beta_norm": 47, 
            "walltime": 7.175
        }, 
        {
            "slope": -0.041007, 
            "first_right_norm": 7.9373, 
            "instance": 83, 
            "beta": 49, 
            "beta_norm": 49, 
            "walltime": 9.779
        }, 
        {
            "slope": -0.042554, 
            "first_right_norm": 7.9373, 
            "instance": 92, 
            "beta": 47, 
            "beta_norm": 47, 
            "walltime": 6.838
        }, 
        {
            "slope": -0.041817, 
            "first_right_norm": 7.9373, 
            "instance": 80, 
            "beta": 52, 
            "beta_norm": 52, 
            "walltime": 13.527
        }, 
        {
            "slope": -0.042331, 
            "first_right_norm": 7.9373, 
            "instance": 91, 
            "beta": 48, 
            "beta_norm": 48, 
            "walltime": 8.111
        }, 
        {
            "slope": -0.04125, 
            "first_right_norm": 7.9373, 
            "instance": 88, 
            "beta": 49, 
            "beta_norm": 49, 
            "walltime": 9.635
        }, 
        {
            "slope": -0.042852, 
            "first_right_norm": 7.9373, 
            "instance": 93, 
            "beta": 47, 
            "beta_norm": 47, 
            "walltime": 7.211
        }, 
        {
            "slope": -0.041815, 
            "first_right_norm": 7.9373, 
            "instance": 86, 
            "beta": 51, 
            "beta_norm": 51, 
            "walltime": 11.983
        }, 
        {
            "slope": -0.042102, 
            "first_right_norm": 7.9373, 
            "instance": 90, 
            "beta": 50, 
            "beta_norm": 50, 
            "walltime": 10.618
        }, 
        {
            "slope": -0.042292, 
            "first_right_norm": 7.9373, 
            "instance": 94, 
            "beta": 49, 
            "beta_norm": 49, 
            "walltime": 9.281
        }, 
        {
            "slope": -0.041939, 
            "first_right_norm": 7.9373, 
            "instance": 95, 
            "beta": 46, 
            "beta_norm": 46, 
            "walltime": 5.783
        }, 
        {
            "slope": -0.041925, 
            "first_right_norm": 7.9373, 
            "instance": 89, 
            "beta": 51, 
            "beta_norm": 51, 
            "walltime": 12.672
        }, 
        {
            "slope": -0.04258, 
            "first_right_norm": 7.9373, 
            "instance": 97, 
            "beta": 44, 
            "beta_norm": 44, 
            "walltime": 3.823
        }, 
        {
            "slope": -0.041965, 
            "first_right_norm": 7.9373, 
            "instance": 98, 
            "beta": 44, 
            "beta_norm": 44, 
            "walltime": 3.742
        }, 
        {
            "slope": -0.041166, 
            "first_right_norm": 7.9373, 
            "instance": 78, 
            "beta": 55, 
            "beta_norm": 55, 
            "walltime": 20.257
        }, 
        {
            "slope": -0.043735, 
            "first_right_norm": 7.9373, 
            "instance": 102, 
            "beta": 40, 
            "beta_norm": 40, 
            "walltime": 2.537
        }, 
        {
            "slope": -0.042762, 
            "first_right_norm": 7.9373, 
            "instance": 101, 
            "beta": 45, 
            "beta_norm": 45, 
            "walltime": 4.912
        }, 
        {
            "slope": -0.043674, 
            "first_right_norm": 7.9373, 
            "instance": 106, 
            "beta": 43, 
            "beta_norm": 43, 
            "walltime": 3.404
        }, 
        {
            "slope": -0.041705, 
            "first_right_norm": 7.9373, 
            "instance": 96, 
            "beta": 49, 
            "beta_norm": 49, 
            "walltime": 9.654
        }, 
        {
            "slope": -0.042717, 
            "first_right_norm": 7.9373, 
            "instance": 111, 
            "beta": 42, 
            "beta_norm": 42, 
            "walltime": 2.832
        }, 
        {
            "slope": -0.045218, 
            "first_right_norm": 7.9373, 
            "instance": 112, 
            "beta": 35, 
            "beta_norm": 35, 
            "walltime": 1.303
        }, 
        {
            "slope": -0.041398, 
            "first_right_norm": 7.9373, 
            "instance": 103, 
            "beta": 47, 
            "beta_norm": 47, 
            "walltime": 7.086
        }, 
        {
            "slope": -0.042296, 
            "first_right_norm": 7.9373, 
            "instance": 110, 
            "beta": 47, 
            "beta_norm": 47, 
            "walltime": 6.938
        }, 
        {
            "slope": -0.042054, 
            "first_right_norm": 7.9373, 
            "instance": 113, 
            "beta": 44, 
            "beta_norm": 44, 
            "walltime": 3.644
        }, 
        {
            "slope": -0.042569, 
            "first_right_norm": 7.9373, 
            "instance": 107, 
            "beta": 48, 
            "beta_norm": 48, 
            "walltime": 8.426
        }, 
        {
            "slope": -0.041993, 
            "first_right_norm": 7.9373, 
            "instance": 108, 
            "beta": 49, 
            "beta_norm": 49, 
            "walltime": 9.152
        }, 
        {
            "slope": -0.04197, 
            "first_right_norm": 7.9373, 
            "instance": 116, 
            "beta": 43, 
            "beta_norm": 43, 
            "walltime": 3.126
        }, 
        {
            "slope": -0.041398, 
            "first_right_norm": 7.9373, 
            "instance": 109, 
            "beta": 49, 
            "beta_norm": 49, 
            "walltime": 9.427
        }, 
        {
            "slope": -0.041732, 
            "first_right_norm": 7.9373, 
            "instance": 100, 
            "beta": 52, 
            "beta_norm": 52, 
            "walltime": 14.789
        }, 
        {
            "slope": -0.042105, 
            "first_right_norm": 7.9373, 
            "instance": 104, 
            "beta": 52, 
            "beta_norm": 52, 
            "walltime": 13.868
        }, 
        {
            "slope": -0.045116, 
            "first_right_norm": 7.9373, 
            "instance": 123, 
            "beta": 35, 
            "beta_norm": 35, 
            "walltime": 1.297
        }, 
        {
            "slope": -0.042189, 
            "first_right_norm": 7.9373, 
            "instance": 114, 
            "beta": 48, 
            "beta_norm": 48, 
            "walltime": 8.109
        }, 
        {
            "slope": -0.041609, 
            "first_right_norm": 7.9373, 
            "instance": 115, 
            "beta": 49, 
            "beta_norm": 49, 
            "walltime": 9.555
        }, 
        {
            "slope": -0.041969, 
            "first_right_norm": 7.9373, 
            "instance": 99, 
            "beta": 55, 
            "beta_norm": 55, 
            "walltime": 19.308
        }, 
        {
            "slope": -0.042157, 
            "first_right_norm": 7.9373, 
            "instance": 120, 
            "beta": 46, 
            "beta_norm": 46, 
            "walltime": 5.849
        }, 
        {
            "slope": -0.042468, 
            "first_right_norm": 7.9373, 
            "instance": 105, 
            "beta": 53, 
            "beta_norm": 53, 
            "walltime": 16.362
        }, 
        {
            "slope": -0.042546, 
            "first_right_norm": 7.9373, 
            "instance": 121, 
            "beta": 47, 
            "beta_norm": 47, 
            "walltime": 7.396
        }, 
        {
            "slope": -0.041782, 
            "first_right_norm": 7.9373, 
            "instance": 127, 
            "beta": 44, 
            "beta_norm": 44, 
            "walltime": 3.258
        }, 
        {
            "slope": -0.041998, 
            "first_right_norm": 7.9373, 
            "instance": 118, 
            "beta": 50, 
            "beta_norm": 50, 
            "walltime": 10.308
        }, 
        {
            "slope": -0.042857, 
            "first_right_norm": 7.9373, 
            "instance": 129, 
            "beta": 44, 
            "beta_norm": 44, 
            "walltime": 3.791
        }, 
        {
            "slope": -0.043944, 
            "first_right_norm": 7.9373, 
            "instance": 133, 
            "beta": 37, 
            "beta_norm": 37, 
            "walltime": 1.908
        }, 
        {
            "slope": -0.041642, 
            "first_right_norm": 7.9373, 
            "instance": 124, 
            "beta": 49, 
            "beta_norm": 49, 
            "walltime": 9.296
        }, 
        {
            "slope": -0.043163, 
            "first_right_norm": 7.9373, 
            "instance": 134, 
            "beta": 40, 
            "beta_norm": 40, 
            "walltime": 2.371
        }, 
        {
            "slope": -0.04209, 
            "first_right_norm": 7.9373, 
            "instance": 128, 
            "beta": 47, 
            "beta_norm": 47, 
            "walltime": 6.953
        }, 
        {
            "slope": -0.040988, 
            "first_right_norm": 7.9373, 
            "instance": 117, 
            "beta": 53, 
            "beta_norm": 53, 
            "walltime": 15.816
        }, 
        {
            "slope": -0.041589, 
            "first_right_norm": 7.9373, 
            "instance": 122, 
            "beta": 52, 
            "beta_norm": 52, 
            "walltime": 13.537
        }, 
        {
            "slope": -0.042392, 
            "first_right_norm": 7.9373, 
            "instance": 132, 
            "beta": 46, 
            "beta_norm": 46, 
            "walltime": 5.801
        }, 
        {
            "slope": -0.041598, 
            "first_right_norm": 7.9373, 
            "instance": 125, 
            "beta": 53, 
            "beta_norm": 53, 
            "walltime": 15.845
        }, 
        {
            "slope": -0.041348, 
            "first_right_norm": 7.9373, 
            "instance": 126, 
            "beta": 53, 
            "beta_norm": 53, 
            "walltime": 15.553
        }, 
        {
            "slope": -0.04272, 
            "first_right_norm": 7.9373, 
            "instance": 139, 
            "beta": 45, 
            "beta_norm": 45, 
            "walltime": 4.515
        }, 
        {
            "slope": -0.041179, 
            "first_right_norm": 7.9373, 
            "instance": 131, 
            "beta": 52, 
            "beta_norm": 52, 
            "walltime": 13.494
        }, 
        {
            "slope": -0.041972, 
            "first_right_norm": 7.9373, 
            "instance": 141, 
            "beta": 46, 
            "beta_norm": 46, 
            "walltime": 5.617
        }, 
        {
            "slope": -0.041386, 
            "first_right_norm": 7.9373, 
            "instance": 130, 
            "beta": 53, 
            "beta_norm": 53, 
            "walltime": 16.187
        }, 
        {
            "slope": -0.041453, 
            "first_right_norm": 7.9373, 
            "instance": 138, 
            "beta": 49, 
            "beta_norm": 49, 
            "walltime": 9.602
        }, 
        {
            "slope": -0.04365, 
            "first_right_norm": 7.9373, 
            "instance": 145, 
            "beta": 38, 
            "beta_norm": 38, 
            "walltime": 2.177
        }, 
        {
            "slope": -0.042542, 
            "first_right_norm": 7.9373, 
            "instance": 142, 
            "beta": 46, 
            "beta_norm": 46, 
            "walltime": 5.756
        }, 
        {
            "slope": -0.042621, 
            "first_right_norm": 7.9373, 
            "instance": 143, 
            "beta": 47, 
            "beta_norm": 47, 
            "walltime": 6.794
        }, 
        {
            "slope": -0.042617, 
            "first_right_norm": 7.9373, 
            "instance": 144, 
            "beta": 47, 
            "beta_norm": 47, 
            "walltime": 6.841
        }, 
        {
            "slope": -0.041875, 
            "first_right_norm": 7.9373, 
            "instance": 140, 
            "beta": 51, 
            "beta_norm": 51, 
            "walltime": 12.37
        }, 
        {
            "slope": -0.041522, 
            "first_right_norm": 7.9373, 
            "instance": 137, 
            "beta": 53, 
            "beta_norm": 53, 
            "walltime": 15.527
        }, 
        {
            "slope": -0.042001, 
            "first_right_norm": 7.9373, 
            "instance": 136, 
            "beta": 54, 
            "beta_norm": 54, 
            "walltime": 17.468
        }, 
        {
            "slope": -0.042495, 
            "first_right_norm": 7.9373, 
            "instance": 147, 
            "beta": 48, 
            "beta_norm": 48, 
            "walltime": 7.817
        }, 
        {
            "slope": -0.042526, 
            "first_right_norm": 7.9373, 
            "instance": 151, 
            "beta": 43, 
            "beta_norm": 43, 
            "walltime": 3.341
        }, 
        {
            "slope": -0.04307, 
            "first_right_norm": 7.9373, 
            "instance": 153, 
            "beta": 42, 
            "beta_norm": 42, 
            "walltime": 2.837
        }, 
        {
            "slope": -0.043917, 
            "first_right_norm": 7.9373, 
            "instance": 157, 
            "beta": 34, 
            "beta_norm": 34, 
            "walltime": 1.089
        }, 
        {
            "slope": -0.044701, 
            "first_right_norm": 7.9373, 
            "instance": 156, 
            "beta": 36, 
            "beta_norm": 36, 
            "walltime": 1.527
        }, 
        {
            "slope": -0.042077, 
            "first_right_norm": 7.9373, 
            "instance": 146, 
            "beta": 50, 
            "beta_norm": 50, 
            "walltime": 11.275
        }, 
        {
            "slope": -0.042115, 
            "first_right_norm": 7.9373, 
            "instance": 148, 
            "beta": 51, 
            "beta_norm": 51, 
            "walltime": 13.163
        }, 
        {
            "slope": -0.043465, 
            "first_right_norm": 7.9373, 
            "instance": 162, 
            "beta": 39, 
            "beta_norm": 39, 
            "walltime": 2.109
        }, 
        {
            "slope": -0.041936, 
            "first_right_norm": 7.9373, 
            "instance": 149, 
            "beta": 53, 
            "beta_norm": 53, 
            "walltime": 15.464
        }, 
        {
            "slope": -0.04, 
            "first_right_norm": 0.0, 
            "instance": 119, 
            "beta": 0, 
            "beta_norm": 0, 
            "walltime": 42.336
        }, 
        {
            "slope": -0.041952, 
            "first_right_norm": 7.9373, 
            "instance": 160, 
            "beta": 48, 
            "beta_norm": 48, 
            "walltime": 8.057
        }, 
        {
            "slope": -0.041894, 
            "first_right_norm": 7.9373, 
            "instance": 152, 
            "beta": 52, 
            "beta_norm": 52, 
            "walltime": 14.217
        }, 
        {
            "slope": -0.042826, 
            "first_right_norm": 7.9373, 
            "instance": 164, 
            "beta": 36, 
            "beta_norm": 36, 
            "walltime": 1.601
        }, 
        {
            "slope": -0.042201, 
            "first_right_norm": 7.9373, 
            "instance": 159, 
            "beta": 49, 
            "beta_norm": 49, 
            "walltime": 9.248
        }, 
        {
            "slope": -0.041195, 
            "first_right_norm": 7.9373, 
            "instance": 155, 
            "beta": 51, 
            "beta_norm": 51, 
            "walltime": 12.091
        }, 
        {
            "slope": -0.042415, 
            "first_right_norm": 7.9373, 
            "instance": 165, 
            "beta": 43, 
            "beta_norm": 43, 
            "walltime": 3.318
        }, 
        {
            "slope": -0.041059, 
            "first_right_norm": 7.9373, 
            "instance": 158, 
            "beta": 52, 
            "beta_norm": 52, 
            "walltime": 13.228
        }, 
        {
            "slope": -0.0441, 
            "first_right_norm": 7.9373, 
            "instance": 170, 
            "beta": 38, 
            "beta_norm": 38, 
            "walltime": 2.075
        }, 
        {
            "slope": -0.04414, 
            "first_right_norm": 7.9373, 
            "instance": 169, 
            "beta": 40, 
            "beta_norm": 40, 
            "walltime": 2.631
        }, 
        {
            "slope": -0.041001, 
            "first_right_norm": 7.9373, 
            "instance": 150, 
            "beta": 55, 
            "beta_norm": 55, 
            "walltime": 20.611
        }, 
        {
            "slope": -0.044214, 
            "first_right_norm": 7.9373, 
            "instance": 172, 
            "beta": 38, 
            "beta_norm": 38, 
            "walltime": 2.061
        }, 
        {
            "slope": -0.041153, 
            "first_right_norm": 7.9373, 
            "instance": 154, 
            "beta": 54, 
            "beta_norm": 54, 
            "walltime": 18.015
        }, 
        {
            "slope": -0.042335, 
            "first_right_norm": 7.9373, 
            "instance": 166, 
            "beta": 46, 
            "beta_norm": 46, 
            "walltime": 5.94
        }, 
        {
            "slope": -0.042454, 
            "first_right_norm": 7.9373, 
            "instance": 168, 
            "beta": 46, 
            "beta_norm": 46, 
            "walltime": 5.998
        }, 
        {
            "slope": -0.042611, 
            "first_right_norm": 7.9373, 
            "instance": 175, 
            "beta": 44, 
            "beta_norm": 44, 
            "walltime": 3.485
        }, 
        {
            "slope": -0.04291, 
            "first_right_norm": 7.9373, 
            "instance": 176, 
            "beta": 42, 
            "beta_norm": 42, 
            "walltime": 2.845
        }, 
        {
            "slope": -0.043169, 
            "first_right_norm": 7.9373, 
            "instance": 178, 
            "beta": 39, 
            "beta_norm": 39, 
            "walltime": 2.201
        }, 
        {
            "slope": -0.044397, 
            "first_right_norm": 7.9373, 
            "instance": 180, 
            "beta": 34, 
            "beta_norm": 34, 
            "walltime": 1.017
        }, 
        {
            "slope": -0.042023, 
            "first_right_norm": 7.9373, 
            "instance": 177, 
            "beta": 45, 
            "beta_norm": 45, 
            "walltime": 4.659
        }, 
        {
            "slope": -0.042392, 
            "first_right_norm": 7.9373, 
            "instance": 171, 
            "beta": 48, 
            "beta_norm": 48, 
            "walltime": 8.156
        }, 
        {
            "slope": -0.043351, 
            "first_right_norm": 7.9373, 
            "instance": 182, 
            "beta": 38, 
            "beta_norm": 38, 
            "walltime": 2.044
        }, 
        {
            "slope": -0.041151, 
            "first_right_norm": 7.9373, 
            "instance": 135, 
            "beta": 62, 
            "beta_norm": 62, 
            "walltime": 42.453
        }, 
        {
            "slope": -0.041159, 
            "first_right_norm": 7.9373, 
            "instance": 163, 
            "beta": 52, 
            "beta_norm": 52, 
            "walltime": 14.095
        }, 
        {
            "slope": -0.040756, 
            "first_right_norm": 7.9373, 
            "instance": 167, 
            "beta": 51, 
            "beta_norm": 51, 
            "walltime": 13.038
        }, 
        {
            "slope": -0.042284, 
            "first_right_norm": 7.9373, 
            "instance": 184, 
            "beta": 43, 
            "beta_norm": 43, 
            "walltime": 3.336
        }, 
        {
            "slope": -0.041987, 
            "first_right_norm": 7.9373, 
            "instance": 179, 
            "beta": 48, 
            "beta_norm": 48, 
            "walltime": 8.141
        }, 
        {
            "slope": -0.044196, 
            "first_right_norm": 7.9373, 
            "instance": 187, 
            "beta": 41, 
            "beta_norm": 41, 
            "walltime": 2.746
        }, 
        {
            "slope": -0.041899, 
            "first_right_norm": 7.9373, 
            "instance": 174, 
            "beta": 51, 
            "beta_norm": 51, 
            "walltime": 12.701
        }, 
        {
            "slope": -0.043306, 
            "first_right_norm": 7.9373, 
            "instance": 190, 
            "beta": 39, 
            "beta_norm": 39, 
            "walltime": 2.242
        }, 
        {
            "slope": -0.042085, 
            "first_right_norm": 7.9373, 
            "instance": 189, 
            "beta": 44, 
            "beta_norm": 44, 
            "walltime": 3.918
        }, 
        {
            "slope": -0.041684, 
            "first_right_norm": 7.9373, 
            "instance": 188, 
            "beta": 46, 
            "beta_norm": 46, 
            "walltime": 5.625
        }, 
        {
            "slope": -0.04271, 
            "first_right_norm": 7.9373, 
            "instance": 192, 
            "beta": 45, 
            "beta_norm": 45, 
            "walltime": 4.248
        }, 
        {
            "slope": -0.041607, 
            "first_right_norm": 7.9373, 
            "instance": 161, 
            "beta": 59, 
            "beta_norm": 59, 
            "walltime": 29.898
        }, 
        {
            "slope": -0.041966, 
            "first_right_norm": 7.9373, 
            "instance": 181, 
            "beta": 51, 
            "beta_norm": 51, 
            "walltime": 12.366
        }, 
        {
            "slope": -0.042186, 
            "first_right_norm": 7.9373, 
            "instance": 183, 
            "beta": 50, 
            "beta_norm": 50, 
            "walltime": 11.301
        }, 
        {
            "slope": -0.041821, 
            "first_right_norm": 7.9373, 
            "instance": 194, 
            "beta": 46, 
            "beta_norm": 46, 
            "walltime": 5.542
        }, 
        {
            "slope": -0.042082, 
            "first_right_norm": 7.9373, 
            "instance": 196, 
            "beta": 46, 
            "beta_norm": 46, 
            "walltime": 5.663
        }, 
        {
            "slope": -0.042169, 
            "first_right_norm": 7.9373, 
            "instance": 195, 
            "beta": 47, 
            "beta_norm": 47, 
            "walltime": 7.191
        }, 
        {
            "slope": -0.042178, 
            "first_right_norm": 7.9373, 
            "instance": 185, 
            "beta": 52, 
            "beta_norm": 52, 
            "walltime": 14.008
        }, 
        {
            "slope": -0.044295, 
            "first_right_norm": 7.9373, 
            "instance": 201, 
            "beta": 36, 
            "beta_norm": 36, 
            "walltime": 1.53
        }, 
        {
            "slope": -0.042348, 
            "first_right_norm": 7.9373, 
            "instance": 197, 
            "beta": 46, 
            "beta_norm": 46, 
            "walltime": 5.923
        }, 
        {
            "slope": -0.04179, 
            "first_right_norm": 7.9373, 
            "instance": 173, 
            "beta": 56, 
            "beta_norm": 56, 
            "walltime": 23.391
        }, 
        {
            "slope": -0.043416, 
            "first_right_norm": 7.9373, 
            "instance": 202, 
            "beta": 40, 
            "beta_norm": 40, 
            "walltime": 2.551
        }, 
        {
            "slope": -0.043612, 
            "first_right_norm": 7.9373, 
            "instance": 203, 
            "beta": 42, 
            "beta_norm": 42, 
            "walltime": 3.074
        }, 
        {
            "slope": -0.041642, 
            "first_right_norm": 7.9373, 
            "instance": 193, 
            "beta": 51, 
            "beta_norm": 51, 
            "walltime": 12.394
        }, 
        {
            "slope": -0.042977, 
            "first_right_norm": 7.9373, 
            "instance": 205, 
            "beta": 44, 
            "beta_norm": 44, 
            "walltime": 3.583
        }, 
        {
            "slope": -0.042097, 
            "first_right_norm": 7.9373, 
            "instance": 206, 
            "beta": 45, 
            "beta_norm": 45, 
            "walltime": 4.534
        }, 
        {
            "slope": -0.043626, 
            "first_right_norm": 7.9373, 
            "instance": 209, 
            "beta": 39, 
            "beta_norm": 39, 
            "walltime": 2.126
        }, 
        {
            "slope": -0.042259, 
            "first_right_norm": 7.9373, 
            "instance": 210, 
            "beta": 45, 
            "beta_norm": 45, 
            "walltime": 4.391
        }, 
        {
            "slope": -0.041662, 
            "first_right_norm": 7.9373, 
            "instance": 186, 
            "beta": 56, 
            "beta_norm": 56, 
            "walltime": 23.565
        }, 
        {
            "slope": -0.042625, 
            "first_right_norm": 7.9373, 
            "instance": 212, 
            "beta": 43, 
            "beta_norm": 43, 
            "walltime": 3.178
        }, 
        {
            "slope": -0.041366, 
            "first_right_norm": 7.9373, 
            "instance": 191, 
            "beta": 56, 
            "beta_norm": 56, 
            "walltime": 20.57
        }, 
        {
            "slope": -0.041463, 
            "first_right_norm": 7.9373, 
            "instance": 198, 
            "beta": 53, 
            "beta_norm": 53, 
            "walltime": 14.533
        }, 
        {
            "slope": -0.0421, 
            "first_right_norm": 7.9373, 
            "instance": 199, 
            "beta": 52, 
            "beta_norm": 52, 
            "walltime": 14.319
        }, 
        {
            "slope": -0.044316, 
            "first_right_norm": 7.9373, 
            "instance": 214, 
            "beta": 39, 
            "beta_norm": 39, 
            "walltime": 2.454
        }, 
        {
            "slope": -0.041915, 
            "first_right_norm": 7.9373, 
            "instance": 200, 
            "beta": 53, 
            "beta_norm": 53, 
            "walltime": 15.68
        }, 
        {
            "slope": -0.044083, 
            "first_right_norm": 7.9373, 
            "instance": 218, 
            "beta": 36, 
            "beta_norm": 36, 
            "walltime": 1.527
        }, 
        {
            "slope": -0.043843, 
            "first_right_norm": 7.9373, 
            "instance": 217, 
            "beta": 41, 
            "beta_norm": 41, 
            "walltime": 2.693
        }, 
        {
            "slope": -0.042398, 
            "first_right_norm": 7.9373, 
            "instance": 213, 
            "beta": 48, 
            "beta_norm": 48, 
            "walltime": 8.155
        }, 
        {
            "slope": -0.043156, 
            "first_right_norm": 7.9373, 
            "instance": 222, 
            "beta": 36, 
            "beta_norm": 36, 
            "walltime": 1.489
        }, 
        {
            "slope": -0.041187, 
            "first_right_norm": 7.9373, 
            "instance": 204, 
            "beta": 53, 
            "beta_norm": 53, 
            "walltime": 16.599
        }, 
        {
            "slope": -0.041991, 
            "first_right_norm": 7.9373, 
            "instance": 207, 
            "beta": 53, 
            "beta_norm": 53, 
            "walltime": 15.615
        }, 
        {
            "slope": -0.04271, 
            "first_right_norm": 7.9373, 
            "instance": 223, 
            "beta": 43, 
            "beta_norm": 43, 
            "walltime": 3.284
        }, 
        {
            "slope": -0.041941, 
            "first_right_norm": 7.9373, 
            "instance": 219, 
            "beta": 47, 
            "beta_norm": 47, 
            "walltime": 7.302
        }, 
        {
            "slope": -0.043797, 
            "first_right_norm": 7.9373, 
            "instance": 226, 
            "beta": 36, 
            "beta_norm": 36, 
            "walltime": 1.636
        }, 
        {
            "slope": -0.041899, 
            "first_right_norm": 7.9373, 
            "instance": 220, 
            "beta": 47, 
            "beta_norm": 47, 
            "walltime": 6.969
        }, 
        {
            "slope": -0.041606, 
            "first_right_norm": 7.9373, 
            "instance": 208, 
            "beta": 55, 
            "beta_norm": 55, 
            "walltime": 19.159
        }, 
        {
            "slope": -0.043286, 
            "first_right_norm": 7.9373, 
            "instance": 230, 
            "beta": 41, 
            "beta_norm": 41, 
            "walltime": 2.733
        }, 
        {
            "slope": -0.041322, 
            "first_right_norm": 7.9373, 
            "instance": 211, 
            "beta": 54, 
            "beta_norm": 54, 
            "walltime": 17.92
        }, 
        {
            "slope": -0.041522, 
            "first_right_norm": 7.9373, 
            "instance": 215, 
            "beta": 51, 
            "beta_norm": 51, 
            "walltime": 12.27
        }, 
        {
            "slope": -0.041118, 
            "first_right_norm": 7.9373, 
            "instance": 216, 
            "beta": 51, 
            "beta_norm": 51, 
            "walltime": 12.199
        }, 
        {
            "slope": -0.043339, 
            "first_right_norm": 7.9373, 
            "instance": 227, 
            "beta": 46, 
            "beta_norm": 46, 
            "walltime": 5.582
        }, 
        {
            "slope": -0.042534, 
            "first_right_norm": 7.9373, 
            "instance": 231, 
            "beta": 44, 
            "beta_norm": 44, 
            "walltime": 3.615
        }, 
        {
            "slope": -0.041532, 
            "first_right_norm": 7.9373, 
            "instance": 228, 
            "beta": 46, 
            "beta_norm": 46, 
            "walltime": 5.709
        }, 
        {
            "slope": -0.043253, 
            "first_right_norm": 7.9373, 
            "instance": 234, 
            "beta": 34, 
            "beta_norm": 34, 
            "walltime": 1.277
        }, 
        {
            "slope": -0.041736, 
            "first_right_norm": 7.9373, 
            "instance": 224, 
            "beta": 49, 
            "beta_norm": 49, 
            "walltime": 9.695
        }, 
        {
            "slope": -0.043731, 
            "first_right_norm": 7.9373, 
            "instance": 238, 
            "beta": 36, 
            "beta_norm": 36, 
            "walltime": 1.545
        }, 
        {
            "slope": -0.043406, 
            "first_right_norm": 7.9373, 
            "instance": 239, 
            "beta": 39, 
            "beta_norm": 39, 
            "walltime": 2.101
        }, 
        {
            "slope": -0.043488, 
            "first_right_norm": 7.9373, 
            "instance": 240, 
            "beta": 40, 
            "beta_norm": 40, 
            "walltime": 2.407
        }, 
        {
            "slope": -0.044109, 
            "first_right_norm": 7.9373, 
            "instance": 242, 
            "beta": 35, 
            "beta_norm": 35, 
            "walltime": 1.385
        }, 
        {
            "slope": -0.042124, 
            "first_right_norm": 7.9373, 
            "instance": 225, 
            "beta": 51, 
            "beta_norm": 51, 
            "walltime": 12.565
        }, 
        {
            "slope": -0.041603, 
            "first_right_norm": 7.9373, 
            "instance": 237, 
            "beta": 46, 
            "beta_norm": 46, 
            "walltime": 5.701
        }, 
        {
            "slope": -0.040962, 
            "first_right_norm": 7.9373, 
            "instance": 235, 
            "beta": 47, 
            "beta_norm": 47, 
            "walltime": 7.23
        }, 
        {
            "slope": -0.041308, 
            "first_right_norm": 7.9373, 
            "instance": 221, 
            "beta": 55, 
            "beta_norm": 55, 
            "walltime": 19.329
        }, 
        {
            "slope": -0.041591, 
            "first_right_norm": 7.9373, 
            "instance": 241, 
            "beta": 47, 
            "beta_norm": 47, 
            "walltime": 6.812
        }, 
        {
            "slope": -0.042448, 
            "first_right_norm": 7.9373, 
            "instance": 233, 
            "beta": 49, 
            "beta_norm": 49, 
            "walltime": 9.664
        }, 
        {
            "slope": -0.042599, 
            "first_right_norm": 7.9373, 
            "instance": 236, 
            "beta": 49, 
            "beta_norm": 49, 
            "walltime": 9.501
        }, 
        {
            "slope": -0.04186, 
            "first_right_norm": 7.9373, 
            "instance": 244, 
            "beta": 46, 
            "beta_norm": 46, 
            "walltime": 5.532
        }, 
        {
            "slope": -0.042272, 
            "first_right_norm": 7.9373, 
            "instance": 243, 
            "beta": 47, 
            "beta_norm": 47, 
            "walltime": 6.948
        }, 
        {
            "slope": -0.045062, 
            "first_right_norm": 7.9373, 
            "instance": 252, 
            "beta": 34, 
            "beta_norm": 34, 
            "walltime": 1.024
        }, 
        {
            "slope": -0.045692, 
            "first_right_norm": 7.9373, 
            "instance": 250, 
            "beta": 34, 
            "beta_norm": 34, 
            "walltime": 1.193
        }, 
        {
            "slope": -0.042861, 
            "first_right_norm": 7.9373, 
            "instance": 253, 
            "beta": 43, 
            "beta_norm": 43, 
            "walltime": 3.2
        }, 
        {
            "slope": -0.046065, 
            "first_right_norm": 7.9373, 
            "instance": 257, 
            "beta": 34, 
            "beta_norm": 34, 
            "walltime": 1.053
        }, 
        {
            "slope": -0.042789, 
            "first_right_norm": 7.9373, 
            "instance": 255, 
            "beta": 45, 
            "beta_norm": 45, 
            "walltime": 4.43
        }, 
        {
            "slope": -0.044765, 
            "first_right_norm": 7.9373, 
            "instance": 259, 
            "beta": 38, 
            "beta_norm": 38, 
            "walltime": 2.021
        }, 
        {
            "slope": -0.042125, 
            "first_right_norm": 7.9373, 
            "instance": 249, 
            "beta": 49, 
            "beta_norm": 49, 
            "walltime": 9.601
        }, 
        {
            "slope": -0.041141, 
            "first_right_norm": 7.9373, 
            "instance": 232, 
            "beta": 55, 
            "beta_norm": 55, 
            "walltime": 21.125
        }, 
        {
            "slope": -0.042132, 
            "first_right_norm": 7.9373, 
            "instance": 245, 
            "beta": 53, 
            "beta_norm": 53, 
            "walltime": 15.195
        }, 
        {
            "slope": -0.041062, 
            "first_right_norm": 7.9373, 
            "instance": 229, 
            "beta": 57, 
            "beta_norm": 57, 
            "walltime": 25.284
        }, 
        {
            "slope": -0.044995, 
            "first_right_norm": 7.9373, 
            "instance": 262, 
            "beta": 34, 
            "beta_norm": 34, 
            "walltime": 1.128
        }, 
        {
            "slope": -0.041935, 
            "first_right_norm": 7.9373, 
            "instance": 248, 
            "beta": 52, 
            "beta_norm": 52, 
            "walltime": 14.074
        }, 
        {
            "slope": -0.043757, 
            "first_right_norm": 7.9373, 
            "instance": 260, 
            "beta": 38, 
            "beta_norm": 38, 
            "walltime": 2.004
        }, 
        {
            "slope": -0.041991, 
            "first_right_norm": 7.9373, 
            "instance": 246, 
            "beta": 54, 
            "beta_norm": 54, 
            "walltime": 18.23
        }, 
        {
            "slope": -0.04142, 
            "first_right_norm": 7.9373, 
            "instance": 254, 
            "beta": 51, 
            "beta_norm": 51, 
            "walltime": 12.099
        }, 
        {
            "slope": -0.043228, 
            "first_right_norm": 7.9373, 
            "instance": 266, 
            "beta": 41, 
            "beta_norm": 41, 
            "walltime": 2.716
        }, 
        {
            "slope": -0.041853, 
            "first_right_norm": 7.9373, 
            "instance": 256, 
            "beta": 52, 
            "beta_norm": 52, 
            "walltime": 14.475
        }, 
        {
            "slope": -0.042978, 
            "first_right_norm": 7.9373, 
            "instance": 268, 
            "beta": 43, 
            "beta_norm": 43, 
            "walltime": 3.243
        }, 
        {
            "slope": -0.042369, 
            "first_right_norm": 7.9373, 
            "instance": 261, 
            "beta": 48, 
            "beta_norm": 48, 
            "walltime": 8.082
        }, 
        {
            "slope": -0.04232, 
            "first_right_norm": 7.9373, 
            "instance": 258, 
            "beta": 51, 
            "beta_norm": 51, 
            "walltime": 13.022
        }, 
        {
            "slope": -0.04175, 
            "first_right_norm": 7.9373, 
            "instance": 267, 
            "beta": 49, 
            "beta_norm": 49, 
            "walltime": 8.861
        }, 
        {
            "slope": -0.041294, 
            "first_right_norm": 7.9373, 
            "instance": 264, 
            "beta": 50, 
            "beta_norm": 50, 
            "walltime": 10.848
        }, 
        {
            "slope": -0.041184, 
            "first_right_norm": 7.9373, 
            "instance": 263, 
            "beta": 50, 
            "beta_norm": 50, 
            "walltime": 11.505
        }, 
        {
            "slope": -0.041746, 
            "first_right_norm": 7.9373, 
            "instance": 271, 
            "beta": 47, 
            "beta_norm": 47, 
            "walltime": 6.845
        }, 
        {
            "slope": -0.042158, 
            "first_right_norm": 7.9373, 
            "instance": 265, 
            "beta": 51, 
            "beta_norm": 51, 
            "walltime": 12.854
        }, 
        {
            "slope": -0.041717, 
            "first_right_norm": 7.9373, 
            "instance": 269, 
            "beta": 50, 
            "beta_norm": 50, 
            "walltime": 10.612
        }, 
        {
            "slope": -0.04178, 
            "first_right_norm": 7.9373, 
            "instance": 247, 
            "beta": 58, 
            "beta_norm": 58, 
            "walltime": 28.254
        }, 
        {
            "slope": -0.044312, 
            "first_right_norm": 7.9373, 
            "instance": 278, 
            "beta": 38, 
            "beta_norm": 38, 
            "walltime": 1.968
        }, 
        {
            "slope": -0.042361, 
            "first_right_norm": 7.9373, 
            "instance": 273, 
            "beta": 48, 
            "beta_norm": 48, 
            "walltime": 8.181
        }, 
        {
            "slope": -0.042093, 
            "first_right_norm": 7.9373, 
            "instance": 270, 
            "beta": 50, 
            "beta_norm": 50, 
            "walltime": 10.948
        }, 
        {
            "slope": -0.04145, 
            "first_right_norm": 7.9373, 
            "instance": 277, 
            "beta": 45, 
            "beta_norm": 45, 
            "walltime": 4.937
        }, 
        {
            "slope": -0.045649, 
            "first_right_norm": 7.9373, 
            "instance": 284, 
            "beta": 33, 
            "beta_norm": 33, 
            "walltime": 0.999
        }, 
        {
            "slope": -0.041417, 
            "first_right_norm": 7.9373, 
            "instance": 251, 
            "beta": 58, 
            "beta_norm": 58, 
            "walltime": 28.849
        }, 
        {
            "slope": -0.042873, 
            "first_right_norm": 7.9373, 
            "instance": 281, 
            "beta": 43, 
            "beta_norm": 43, 
            "walltime": 3.381
        }, 
        {
            "slope": -0.041124, 
            "first_right_norm": 7.9373, 
            "instance": 272, 
            "beta": 51, 
            "beta_norm": 51, 
            "walltime": 12.338
        }, 
        {
            "slope": -0.042117, 
            "first_right_norm": 7.9373, 
            "instance": 274, 
            "beta": 49, 
            "beta_norm": 49, 
            "walltime": 9.891
        }, 
        {
            "slope": -0.041982, 
            "first_right_norm": 7.9373, 
            "instance": 279, 
            "beta": 45, 
            "beta_norm": 45, 
            "walltime": 4.881
        }, 
        {
            "slope": -0.043211, 
            "first_right_norm": 7.9373, 
            "instance": 285, 
            "beta": 40, 
            "beta_norm": 40, 
            "walltime": 2.603
        }, 
        {
            "slope": -0.041931, 
            "first_right_norm": 7.9373, 
            "instance": 276, 
            "beta": 49, 
            "beta_norm": 49, 
            "walltime": 9.684
        }, 
        {
            "slope": -0.042705, 
            "first_right_norm": 7.9373, 
            "instance": 287, 
            "beta": 43, 
            "beta_norm": 43, 
            "walltime": 3.272
        }, 
        {
            "slope": -0.044618, 
            "first_right_norm": 7.9373, 
            "instance": 292, 
            "beta": 35, 
            "beta_norm": 35, 
            "walltime": 1.3
        }, 
        {
            "slope": -0.041846, 
            "first_right_norm": 7.9373, 
            "instance": 275, 
            "beta": 50, 
            "beta_norm": 50, 
            "walltime": 11.249
        }, 
        {
            "slope": -0.044237, 
            "first_right_norm": 7.9373, 
            "instance": 291, 
            "beta": 40, 
            "beta_norm": 40, 
            "walltime": 2.66
        }, 
        {
            "slope": -0.045801, 
            "first_right_norm": 7.9373, 
            "instance": 294, 
            "beta": 32, 
            "beta_norm": 32, 
            "walltime": 0.813
        }, 
        {
            "slope": -0.041826, 
            "first_right_norm": 7.9373, 
            "instance": 280, 
            "beta": 50, 
            "beta_norm": 50, 
            "walltime": 10.8
        }, 
        {
            "slope": -0.043807, 
            "first_right_norm": 7.9373, 
            "instance": 298, 
            "beta": 38, 
            "beta_norm": 38, 
            "walltime": 1.968
        }, 
        {
            "slope": -0.042198, 
            "first_right_norm": 7.9373, 
            "instance": 296, 
            "beta": 43, 
            "beta_norm": 43, 
            "walltime": 3.174
        }, 
        {
            "slope": -0.041401, 
            "first_right_norm": 7.9373, 
            "instance": 288, 
            "beta": 48, 
            "beta_norm": 48, 
            "walltime": 7.959
        }, 
        {
            "slope": -0.045509, 
            "first_right_norm": 7.9373, 
            "instance": 299, 
            "beta": 34, 
            "beta_norm": 34, 
            "walltime": 1.08
        }, 
        {
            "slope": -0.044854, 
            "first_right_norm": 7.9373, 
            "instance": 300, 
            "beta": 35, 
            "beta_norm": 35, 
            "walltime": 1.291
        }, 
        {
            "slope": -0.04145, 
            "first_right_norm": 7.9373, 
            "instance": 297, 
            "beta": 49, 
            "beta_norm": 49, 
            "walltime": 8.566
        }, 
        {
            "slope": -0.04166, 
            "first_right_norm": 7.9373, 
            "instance": 293, 
            "beta": 50, 
            "beta_norm": 50, 
            "walltime": 10.759
        }, 
        {
            "slope": -0.041801, 
            "first_right_norm": 7.9373, 
            "instance": 283, 
            "beta": 54, 
            "beta_norm": 54, 
            "walltime": 17.094
        }, 
        {
            "slope": -0.041562, 
            "first_right_norm": 7.9373, 
            "instance": 289, 
            "beta": 53, 
            "beta_norm": 53, 
            "walltime": 16.119
        }, 
        {
            "slope": -0.042213, 
            "first_right_norm": 7.9373, 
            "instance": 290, 
            "beta": 54, 
            "beta_norm": 54, 
            "walltime": 16.831
        }, 
        {
            "slope": -0.041114, 
            "first_right_norm": 7.9373, 
            "instance": 286, 
            "beta": 56, 
            "beta_norm": 56, 
            "walltime": 21.185
        }, 
        {
            "slope": -0.041516, 
            "first_right_norm": 7.9373, 
            "instance": 282, 
            "beta": 60, 
            "beta_norm": 60, 
            "walltime": 31.005
        }, 
        {
            "slope": -0.0403, 
            "first_right_norm": 0.0, 
            "instance": 295, 
            "beta": 0, 
            "beta_norm": 0, 
            "walltime": 43.011
        }
    ], 
    "problem_dimension": 62
}