{
    "total_running_time": 2306.854, 
    "num_instances": 300, 
    "N": "16", 
    "results": [
        {
            "walltime": 3.636, 
            "slope": -0.040793, 
            "beta": 24, 
            "instance": 1
        }, 
        {
            "walltime": 6.817, 
            "slope": -0.039218, 
            "beta": 42, 
            "instance": 2
        }, 
        {
            "walltime": 6.509, 
            "slope": -0.038477, 
            "beta": 40, 
            "instance": 3
        }, 
        {
            "walltime": 4.655, 
            "slope": -0.040047, 
            "beta": 30, 
            "instance": 4
        }, 
        {
            "walltime": 14.232, 
            "slope": -0.037777, 
            "beta": 53, 
            "instance": 5
        }, 
        {
            "walltime": 5.142, 
            "slope": -0.038965, 
            "beta": 33, 
            "instance": 6
        }, 
        {
            "walltime": 6.847, 
            "slope": -0.038651, 
            "beta": 41, 
            "instance": 7
        }, 
        {
            "walltime": 5.136, 
            "slope": -0.039175, 
            "beta": 33, 
            "instance": 8
        }, 
        {
            "walltime": 9.714, 
            "slope": -0.037706, 
            "beta": 47, 
            "instance": 9
        }, 
        {
            "walltime": 4.422, 
            "slope": -0.040429, 
            "beta": 28, 
            "instance": 10
        }, 
        {
            "walltime": 6.201, 
            "slope": -0.038316, 
            "beta": 39, 
            "instance": 11
        }, 
        {
            "walltime": 7.088, 
            "slope": -0.038203, 
            "beta": 43, 
            "instance": 12
        }, 
        {
            "walltime": 18.695, 
            "slope": -0.037171, 
            "beta": 0, 
            "instance": 13
        }, 
        {
            "walltime": 5.438, 
            "slope": -0.040221, 
            "beta": 34, 
            "instance": 14
        }, 
        {
            "walltime": 6.461, 
            "slope": -0.039276, 
            "beta": 39, 
            "instance": 15
        }, 
        {
            "walltime": 9.523, 
            "slope": -0.03853, 
            "beta": 47, 
            "instance": 16
        }, 
        {
            "walltime": 6.894, 
            "slope": -0.037802, 
            "beta": 42, 
            "instance": 17
        }, 
        {
            "walltime": 5.724, 
            "slope": -0.037957, 
            "beta": 36, 
            "instance": 18
        }, 
        {
            "walltime": 5.906, 
            "slope": -0.039578, 
            "beta": 37, 
            "instance": 19
        }, 
        {
            "walltime": 7.261, 
            "slope": -0.037519, 
            "beta": 43, 
            "instance": 20
        }, 
        {
            "walltime": 6.788, 
            "slope": -0.036883, 
            "beta": 42, 
            "instance": 21
        }, 
        {
            "walltime": 2.753, 
            "slope": -0.040223, 
            "beta": 18, 
            "instance": 22
        }, 
        {
            "walltime": 7.399, 
            "slope": -0.037819, 
            "beta": 44, 
            "instance": 23
        }, 
        {
            "walltime": 5.26, 
            "slope": -0.039082, 
            "beta": 33, 
            "instance": 24
        }, 
        {
            "walltime": 6.839, 
            "slope": -0.039005, 
            "beta": 41, 
            "instance": 25
        }, 
        {
            "walltime": 5.494, 
            "slope": -0.038589, 
            "beta": 35, 
            "instance": 26
        }, 
        {
            "walltime": 18.185, 
            "slope": -0.037228, 
            "beta": 0, 
            "instance": 27
        }, 
        {
            "walltime": 7.033, 
            "slope": -0.037657, 
            "beta": 42, 
            "instance": 28
        }, 
        {
            "walltime": 5.696, 
            "slope": -0.039066, 
            "beta": 36, 
            "instance": 29
        }, 
        {
            "walltime": 6.29, 
            "slope": -0.037844, 
            "beta": 39, 
            "instance": 30
        }, 
        {
            "walltime": 6.756, 
            "slope": -0.03787, 
            "beta": 41, 
            "instance": 31
        }, 
        {
            "walltime": 3.219, 
            "slope": -0.040981, 
            "beta": 21, 
            "instance": 32
        }, 
        {
            "walltime": 2.86, 
            "slope": -0.043873, 
            "beta": 19, 
            "instance": 33
        }, 
        {
            "walltime": 8.68, 
            "slope": -0.037555, 
            "beta": 46, 
            "instance": 34
        }, 
        {
            "walltime": 6.272, 
            "slope": -0.037674, 
            "beta": 39, 
            "instance": 35
        }, 
        {
            "walltime": 18.123, 
            "slope": -0.036768, 
            "beta": 0, 
            "instance": 36
        }, 
        {
            "walltime": 6.241, 
            "slope": -0.03903, 
            "beta": 39, 
            "instance": 37
        }, 
        {
            "walltime": 4.464, 
            "slope": -0.040252, 
            "beta": 29, 
            "instance": 38
        }, 
        {
            "walltime": 7.132, 
            "slope": -0.038219, 
            "beta": 43, 
            "instance": 39
        }, 
        {
            "walltime": 12.458, 
            "slope": -0.037801, 
            "beta": 51, 
            "instance": 40
        }, 
        {
            "walltime": 6.523, 
            "slope": -0.037831, 
            "beta": 40, 
            "instance": 41
        }, 
        {
            "walltime": 17.725, 
            "slope": -0.036647, 
            "beta": 0, 
            "instance": 42
        }, 
        {
            "walltime": 4.677, 
            "slope": -0.039695, 
            "beta": 30, 
            "instance": 43
        }, 
        {
            "walltime": 5.89, 
            "slope": -0.039223, 
            "beta": 37, 
            "instance": 44
        }, 
        {
            "walltime": 8.683, 
            "slope": -0.03729, 
            "beta": 46, 
            "instance": 45
        }, 
        {
            "walltime": 8.023, 
            "slope": -0.038556, 
            "beta": 45, 
            "instance": 46
        }, 
        {
            "walltime": 5.851, 
            "slope": -0.038101, 
            "beta": 36, 
            "instance": 47
        }, 
        {
            "walltime": 6.545, 
            "slope": -0.037647, 
            "beta": 40, 
            "instance": 48
        }, 
        {
            "walltime": 4.651, 
            "slope": -0.040106, 
            "beta": 30, 
            "instance": 49
        }, 
        {
            "walltime": 5.857, 
            "slope": -0.038098, 
            "beta": 36, 
            "instance": 50
        }, 
        {
            "walltime": 5.965, 
            "slope": -0.038842, 
            "beta": 37, 
            "instance": 51
        }, 
        {
            "walltime": 6.249, 
            "slope": -0.038728, 
            "beta": 39, 
            "instance": 52
        }, 
        {
            "walltime": 6.525, 
            "slope": -0.038991, 
            "beta": 40, 
            "instance": 53
        }, 
        {
            "walltime": 5.639, 
            "slope": -0.039721, 
            "beta": 36, 
            "instance": 54
        }, 
        {
            "walltime": 10.214, 
            "slope": -0.037247, 
            "beta": 48, 
            "instance": 55
        }, 
        {
            "walltime": 7.01, 
            "slope": -0.037864, 
            "beta": 43, 
            "instance": 56
        }, 
        {
            "walltime": 7.296, 
            "slope": -0.038022, 
            "beta": 44, 
            "instance": 57
        }, 
        {
            "walltime": 7.106, 
            "slope": -0.038318, 
            "beta": 43, 
            "instance": 58
        }, 
        {
            "walltime": 9.59, 
            "slope": -0.037388, 
            "beta": 47, 
            "instance": 59
        }, 
        {
            "walltime": 8.793, 
            "slope": -0.037533, 
            "beta": 46, 
            "instance": 60
        }, 
        {
            "walltime": 6.04, 
            "slope": -0.038862, 
            "beta": 38, 
            "instance": 61
        }, 
        {
            "walltime": 4.636, 
            "slope": -0.038174, 
            "beta": 30, 
            "instance": 62
        }, 
        {
            "walltime": 8.234, 
            "slope": -0.037748, 
            "beta": 45, 
            "instance": 63
        }, 
        {
            "walltime": 5.804, 
            "slope": -0.038873, 
            "beta": 36, 
            "instance": 64
        }, 
        {
            "walltime": 6.857, 
            "slope": -0.038851, 
            "beta": 41, 
            "instance": 65
        }, 
        {
            "walltime": 7.294, 
            "slope": -0.038245, 
            "beta": 43, 
            "instance": 66
        }, 
        {
            "walltime": 7.959, 
            "slope": -0.038228, 
            "beta": 45, 
            "instance": 67
        }, 
        {
            "walltime": 18.244, 
            "slope": -0.037314, 
            "beta": 0, 
            "instance": 68
        }, 
        {
            "walltime": 6.503, 
            "slope": -0.039504, 
            "beta": 40, 
            "instance": 69
        }, 
        {
            "walltime": 14.307, 
            "slope": -0.037784, 
            "beta": 52, 
            "instance": 70
        }, 
        {
            "walltime": 5.443, 
            "slope": -0.038571, 
            "beta": 34, 
            "instance": 71
        }, 
        {
            "walltime": 6.889, 
            "slope": -0.037529, 
            "beta": 42, 
            "instance": 72
        }, 
        {
            "walltime": 4.245, 
            "slope": -0.040518, 
            "beta": 27, 
            "instance": 73
        }, 
        {
            "walltime": 7.098, 
            "slope": -0.038184, 
            "beta": 43, 
            "instance": 74
        }, 
        {
            "walltime": 7.27, 
            "slope": -0.038841, 
            "beta": 41, 
            "instance": 75
        }, 
        {
            "walltime": 6.336, 
            "slope": -0.038916, 
            "beta": 39, 
            "instance": 76
        }, 
        {
            "walltime": 6.092, 
            "slope": -0.038894, 
            "beta": 38, 
            "instance": 77
        }, 
        {
            "walltime": 4.598, 
            "slope": -0.039807, 
            "beta": 29, 
            "instance": 78
        }, 
        {
            "walltime": 4.014, 
            "slope": -0.040505, 
            "beta": 26, 
            "instance": 79
        }, 
        {
            "walltime": 7.359, 
            "slope": -0.037985, 
            "beta": 44, 
            "instance": 80
        }, 
        {
            "walltime": 6.969, 
            "slope": -0.038905, 
            "beta": 41, 
            "instance": 81
        }, 
        {
            "walltime": 17.466, 
            "slope": -0.036337, 
            "beta": 0, 
            "instance": 82
        }, 
        {
            "walltime": 10.362, 
            "slope": -0.037563, 
            "beta": 48, 
            "instance": 83
        }, 
        {
            "walltime": 4.471, 
            "slope": -0.038975, 
            "beta": 29, 
            "instance": 84
        }, 
        {
            "walltime": 9.859, 
            "slope": -0.037574, 
            "beta": 47, 
            "instance": 85
        }, 
        {
            "walltime": 8.547, 
            "slope": -0.037596, 
            "beta": 46, 
            "instance": 86
        }, 
        {
            "walltime": 6.712, 
            "slope": -0.038973, 
            "beta": 41, 
            "instance": 87
        }, 
        {
            "walltime": 5.802, 
            "slope": -0.039121, 
            "beta": 36, 
            "instance": 88
        }, 
        {
            "walltime": 6.07, 
            "slope": -0.039681, 
            "beta": 38, 
            "instance": 89
        }, 
        {
            "walltime": 5.681, 
            "slope": -0.039739, 
            "beta": 36, 
            "instance": 90
        }, 
        {
            "walltime": 18.238, 
            "slope": -0.037013, 
            "beta": 0, 
            "instance": 91
        }, 
        {
            "walltime": 6.022, 
            "slope": -0.03766, 
            "beta": 38, 
            "instance": 92
        }, 
        {
            "walltime": 6.403, 
            "slope": -0.037501, 
            "beta": 39, 
            "instance": 93
        }, 
        {
            "walltime": 18.449, 
            "slope": -0.037402, 
            "beta": 0, 
            "instance": 94
        }, 
        {
            "walltime": 3.336, 
            "slope": -0.039525, 
            "beta": 22, 
            "instance": 95
        }, 
        {
            "walltime": 4.554, 
            "slope": -0.040376, 
            "beta": 29, 
            "instance": 96
        }, 
        {
            "walltime": 5.321, 
            "slope": -0.040046, 
            "beta": 34, 
            "instance": 97
        }, 
        {
            "walltime": 6.329, 
            "slope": -0.039013, 
            "beta": 39, 
            "instance": 98
        }, 
        {
            "walltime": 10.456, 
            "slope": -0.037903, 
            "beta": 48, 
            "instance": 99
        }, 
        {
            "walltime": 12.79, 
            "slope": -0.037519, 
            "beta": 51, 
            "instance": 100
        }, 
        {
            "walltime": 6.216, 
            "slope": -0.039176, 
            "beta": 38, 
            "instance": 101
        }, 
        {
            "walltime": 6.169, 
            "slope": -0.039669, 
            "beta": 38, 
            "instance": 102
        }, 
        {
            "walltime": 4.849, 
            "slope": -0.039043, 
            "beta": 31, 
            "instance": 103
        }, 
        {
            "walltime": 5.236, 
            "slope": -0.03955, 
            "beta": 33, 
            "instance": 104
        }, 
        {
            "walltime": 6.306, 
            "slope": -0.038686, 
            "beta": 39, 
            "instance": 105
        }, 
        {
            "walltime": 6.068, 
            "slope": -0.037206, 
            "beta": 37, 
            "instance": 106
        }, 
        {
            "walltime": 6.566, 
            "slope": -0.039433, 
            "beta": 40, 
            "instance": 107
        }, 
        {
            "walltime": 17.917, 
            "slope": -0.03705, 
            "beta": 0, 
            "instance": 108
        }, 
        {
            "walltime": 17.487, 
            "slope": -0.036596, 
            "beta": 0, 
            "instance": 109
        }, 
        {
            "walltime": 5.887, 
            "slope": -0.03865, 
            "beta": 37, 
            "instance": 110
        }, 
        {
            "walltime": 5.451, 
            "slope": -0.039772, 
            "beta": 34, 
            "instance": 111
        }, 
        {
            "walltime": 5.28, 
            "slope": -0.039226, 
            "beta": 33, 
            "instance": 112
        }, 
        {
            "walltime": 5.489, 
            "slope": -0.038389, 
            "beta": 35, 
            "instance": 113
        }, 
        {
            "walltime": 13.83, 
            "slope": -0.038027, 
            "beta": 52, 
            "instance": 114
        }, 
        {
            "walltime": 5.998, 
            "slope": -0.039131, 
            "beta": 37, 
            "instance": 115
        }, 
        {
            "walltime": 5.076, 
            "slope": -0.039329, 
            "beta": 32, 
            "instance": 116
        }, 
        {
            "walltime": 5.009, 
            "slope": -0.039978, 
            "beta": 32, 
            "instance": 117
        }, 
        {
            "walltime": 6.021, 
            "slope": -0.038049, 
            "beta": 37, 
            "instance": 118
        }, 
        {
            "walltime": 8.115, 
            "slope": -0.038607, 
            "beta": 45, 
            "instance": 119
        }, 
        {
            "walltime": 9.565, 
            "slope": -0.037406, 
            "beta": 47, 
            "instance": 120
        }, 
        {
            "walltime": 6.407, 
            "slope": -0.03867, 
            "beta": 39, 
            "instance": 121
        }, 
        {
            "walltime": 4.389, 
            "slope": -0.041031, 
            "beta": 28, 
            "instance": 122
        }, 
        {
            "walltime": 7.203, 
            "slope": -0.037636, 
            "beta": 43, 
            "instance": 123
        }, 
        {
            "walltime": 4.717, 
            "slope": -0.040461, 
            "beta": 30, 
            "instance": 124
        }, 
        {
            "walltime": 10.278, 
            "slope": -0.037192, 
            "beta": 48, 
            "instance": 125
        }, 
        {
            "walltime": 11.455, 
            "slope": -0.037674, 
            "beta": 49, 
            "instance": 126
        }, 
        {
            "walltime": 6.782, 
            "slope": -0.038399, 
            "beta": 41, 
            "instance": 127
        }, 
        {
            "walltime": 18.111, 
            "slope": -0.037526, 
            "beta": 0, 
            "instance": 128
        }, 
        {
            "walltime": 7.309, 
            "slope": -0.037307, 
            "beta": 43, 
            "instance": 129
        }, 
        {
            "walltime": 9.543, 
            "slope": -0.037669, 
            "beta": 47, 
            "instance": 130
        }, 
        {
            "walltime": 5.026, 
            "slope": -0.039852, 
            "beta": 31, 
            "instance": 131
        }, 
        {
            "walltime": 3.972, 
            "slope": -0.041089, 
            "beta": 26, 
            "instance": 132
        }, 
        {
            "walltime": 11.244, 
            "slope": -0.036923, 
            "beta": 49, 
            "instance": 133
        }, 
        {
            "walltime": 4.88, 
            "slope": -0.039255, 
            "beta": 31, 
            "instance": 134
        }, 
        {
            "walltime": 2.872, 
            "slope": -0.041947, 
            "beta": 19, 
            "instance": 135
        }, 
        {
            "walltime": 6.576, 
            "slope": -0.037792, 
            "beta": 40, 
            "instance": 136
        }, 
        {
            "walltime": 7.227, 
            "slope": -0.038909, 
            "beta": 43, 
            "instance": 137
        }, 
        {
            "walltime": 6.776, 
            "slope": -0.03904, 
            "beta": 41, 
            "instance": 138
        }, 
        {
            "walltime": 5.37, 
            "slope": -0.038841, 
            "beta": 34, 
            "instance": 139
        }, 
        {
            "walltime": 5.946, 
            "slope": -0.039226, 
            "beta": 38, 
            "instance": 140
        }, 
        {
            "walltime": 4.571, 
            "slope": -0.040353, 
            "beta": 29, 
            "instance": 141
        }, 
        {
            "walltime": 5.91, 
            "slope": -0.038446, 
            "beta": 37, 
            "instance": 142
        }, 
        {
            "walltime": 5.98, 
            "slope": -0.040396, 
            "beta": 37, 
            "instance": 143
        }, 
        {
            "walltime": 7.021, 
            "slope": -0.037841, 
            "beta": 42, 
            "instance": 144
        }, 
        {
            "walltime": 7.395, 
            "slope": -0.03717, 
            "beta": 44, 
            "instance": 145
        }, 
        {
            "walltime": 3.791, 
            "slope": -0.041161, 
            "beta": 25, 
            "instance": 146
        }, 
        {
            "walltime": 10.969, 
            "slope": -0.03855, 
            "beta": 49, 
            "instance": 147
        }, 
        {
            "walltime": 6.52, 
            "slope": -0.038642, 
            "beta": 40, 
            "instance": 148
        }, 
        {
            "walltime": 6.843, 
            "slope": -0.039034, 
            "beta": 42, 
            "instance": 149
        }, 
        {
            "walltime": 7.578, 
            "slope": -0.037951, 
            "beta": 44, 
            "instance": 150
        }, 
        {
            "walltime": 5.305, 
            "slope": -0.038296, 
            "beta": 34, 
            "instance": 151
        }, 
        {
            "walltime": 5.692, 
            "slope": -0.0376, 
            "beta": 36, 
            "instance": 152
        }, 
        {
            "walltime": 3.97, 
            "slope": -0.041815, 
            "beta": 26, 
            "instance": 153
        }, 
        {
            "walltime": 6.089, 
            "slope": -0.037701, 
            "beta": 38, 
            "instance": 154
        }, 
        {
            "walltime": 6.69, 
            "slope": -0.038081, 
            "beta": 41, 
            "instance": 155
        }, 
        {
            "walltime": 5.949, 
            "slope": -0.038798, 
            "beta": 37, 
            "instance": 156
        }, 
        {
            "walltime": 11.845, 
            "slope": -0.038078, 
            "beta": 50, 
            "instance": 157
        }, 
        {
            "walltime": 17.805, 
            "slope": -0.037482, 
            "beta": 0, 
            "instance": 158
        }, 
        {
            "walltime": 17.599, 
            "slope": -0.036652, 
            "beta": 0, 
            "instance": 159
        }, 
        {
            "walltime": 7.288, 
            "slope": -0.037948, 
            "beta": 43, 
            "instance": 160
        }, 
        {
            "walltime": 6.705, 
            "slope": -0.039095, 
            "beta": 41, 
            "instance": 161
        }, 
        {
            "walltime": 6.414, 
            "slope": -0.038781, 
            "beta": 39, 
            "instance": 162
        }, 
        {
            "walltime": 3.973, 
            "slope": -0.039733, 
            "beta": 26, 
            "instance": 163
        }, 
        {
            "walltime": 7.574, 
            "slope": -0.037871, 
            "beta": 44, 
            "instance": 164
        }, 
        {
            "walltime": 4.868, 
            "slope": -0.039243, 
            "beta": 31, 
            "instance": 165
        }, 
        {
            "walltime": 6.407, 
            "slope": -0.038374, 
            "beta": 39, 
            "instance": 166
        }, 
        {
            "walltime": 16.207, 
            "slope": -0.037673, 
            "beta": 55, 
            "instance": 167
        }, 
        {
            "walltime": 6.299, 
            "slope": -0.037499, 
            "beta": 39, 
            "instance": 168
        }, 
        {
            "walltime": 12.84, 
            "slope": -0.037531, 
            "beta": 51, 
            "instance": 169
        }, 
        {
            "walltime": 11.495, 
            "slope": -0.038005, 
            "beta": 49, 
            "instance": 170
        }, 
        {
            "walltime": 12.277, 
            "slope": -0.038338, 
            "beta": 50, 
            "instance": 171
        }, 
        {
            "walltime": 6.147, 
            "slope": -0.037599, 
            "beta": 38, 
            "instance": 172
        }, 
        {
            "walltime": 5.779, 
            "slope": -0.039669, 
            "beta": 36, 
            "instance": 173
        }, 
        {
            "walltime": 7.312, 
            "slope": -0.03748, 
            "beta": 44, 
            "instance": 174
        }, 
        {
            "walltime": 6.006, 
            "slope": -0.039329, 
            "beta": 37, 
            "instance": 175
        }, 
        {
            "walltime": 5.417, 
            "slope": -0.037644, 
            "beta": 34, 
            "instance": 176
        }, 
        {
            "walltime": 4.745, 
            "slope": -0.038859, 
            "beta": 30, 
            "instance": 177
        }, 
        {
            "walltime": 5.51, 
            "slope": -0.039561, 
            "beta": 35, 
            "instance": 178
        }, 
        {
            "walltime": 7.354, 
            "slope": -0.038002, 
            "beta": 44, 
            "instance": 179
        }, 
        {
            "walltime": 9.709, 
            "slope": -0.038297, 
            "beta": 47, 
            "instance": 180
        }, 
        {
            "walltime": 5.87, 
            "slope": -0.037661, 
            "beta": 37, 
            "instance": 181
        }, 
        {
            "walltime": 5.806, 
            "slope": -0.038039, 
            "beta": 36, 
            "instance": 182
        }, 
        {
            "walltime": 7.359, 
            "slope": -0.037243, 
            "beta": 44, 
            "instance": 183
        }, 
        {
            "walltime": 6.626, 
            "slope": -0.038822, 
            "beta": 39, 
            "instance": 184
        }, 
        {
            "walltime": 5.676, 
            "slope": -0.039504, 
            "beta": 35, 
            "instance": 185
        }, 
        {
            "walltime": 6.898, 
            "slope": -0.037268, 
            "beta": 42, 
            "instance": 186
        }, 
        {
            "walltime": 5.754, 
            "slope": -0.03796, 
            "beta": 36, 
            "instance": 187
        }, 
        {
            "walltime": 19.016, 
            "slope": -0.036793, 
            "beta": 0, 
            "instance": 188
        }, 
        {
            "walltime": 6.074, 
            "slope": -0.037935, 
            "beta": 38, 
            "instance": 189
        }, 
        {
            "walltime": 10.994, 
            "slope": -0.038071, 
            "beta": 49, 
            "instance": 190
        }, 
        {
            "walltime": 8.708, 
            "slope": -0.038818, 
            "beta": 46, 
            "instance": 191
        }, 
        {
            "walltime": 4.611, 
            "slope": -0.040754, 
            "beta": 30, 
            "instance": 192
        }, 
        {
            "walltime": 7.384, 
            "slope": -0.038211, 
            "beta": 44, 
            "instance": 193
        }, 
        {
            "walltime": 4.82, 
            "slope": -0.039879, 
            "beta": 31, 
            "instance": 194
        }, 
        {
            "walltime": 3.859, 
            "slope": -0.040723, 
            "beta": 25, 
            "instance": 195
        }, 
        {
            "walltime": 7.22, 
            "slope": -0.038477, 
            "beta": 43, 
            "instance": 196
        }, 
        {
            "walltime": 7.947, 
            "slope": -0.037789, 
            "beta": 45, 
            "instance": 197
        }, 
        {
            "walltime": 7.026, 
            "slope": -0.038715, 
            "beta": 42, 
            "instance": 198
        }, 
        {
            "walltime": 6.157, 
            "slope": -0.039184, 
            "beta": 38, 
            "instance": 199
        }, 
        {
            "walltime": 8.189, 
            "slope": -0.037719, 
            "beta": 45, 
            "instance": 200
        }, 
        {
            "walltime": 6.742, 
            "slope": -0.038134, 
            "beta": 40, 
            "instance": 201
        }, 
        {
            "walltime": 6.529, 
            "slope": -0.038229, 
            "beta": 40, 
            "instance": 202
        }, 
        {
            "walltime": 7.991, 
            "slope": -0.038065, 
            "beta": 45, 
            "instance": 203
        }, 
        {
            "walltime": 4.092, 
            "slope": -0.042014, 
            "beta": 26, 
            "instance": 204
        }, 
        {
            "walltime": 17.961, 
            "slope": -0.038062, 
            "beta": 55, 
            "instance": 205
        }, 
        {
            "walltime": 6.495, 
            "slope": -0.037403, 
            "beta": 40, 
            "instance": 206
        }, 
        {
            "walltime": 9.53, 
            "slope": -0.037826, 
            "beta": 47, 
            "instance": 207
        }, 
        {
            "walltime": 13.616, 
            "slope": -0.037365, 
            "beta": 52, 
            "instance": 208
        }, 
        {
            "walltime": 6.083, 
            "slope": -0.038839, 
            "beta": 38, 
            "instance": 209
        }, 
        {
            "walltime": 8.076, 
            "slope": -0.037514, 
            "beta": 45, 
            "instance": 210
        }, 
        {
            "walltime": 3.975, 
            "slope": -0.040382, 
            "beta": 25, 
            "instance": 211
        }, 
        {
            "walltime": 6.882, 
            "slope": -0.038718, 
            "beta": 42, 
            "instance": 212
        }, 
        {
            "walltime": 6.335, 
            "slope": -0.038255, 
            "beta": 39, 
            "instance": 213
        }, 
        {
            "walltime": 6.796, 
            "slope": -0.037474, 
            "beta": 42, 
            "instance": 214
        }, 
        {
            "walltime": 5.128, 
            "slope": -0.038993, 
            "beta": 32, 
            "instance": 215
        }, 
        {
            "walltime": 17.752, 
            "slope": -0.037552, 
            "beta": 0, 
            "instance": 216
        }, 
        {
            "walltime": 5.542, 
            "slope": -0.039583, 
            "beta": 35, 
            "instance": 217
        }, 
        {
            "walltime": 6.108, 
            "slope": -0.037941, 
            "beta": 38, 
            "instance": 218
        }, 
        {
            "walltime": 5.963, 
            "slope": -0.037926, 
            "beta": 34, 
            "instance": 219
        }, 
        {
            "walltime": 5.994, 
            "slope": -0.038044, 
            "beta": 38, 
            "instance": 220
        }, 
        {
            "walltime": 10.197, 
            "slope": -0.038085, 
            "beta": 48, 
            "instance": 221
        }, 
        {
            "walltime": 18.502, 
            "slope": -0.03749, 
            "beta": 0, 
            "instance": 222
        }, 
        {
            "walltime": 5.154, 
            "slope": -0.039757, 
            "beta": 33, 
            "instance": 223
        }, 
        {
            "walltime": 7.169, 
            "slope": -0.038304, 
            "beta": 43, 
            "instance": 224
        }, 
        {
            "walltime": 14.501, 
            "slope": -0.038556, 
            "beta": 53, 
            "instance": 225
        }, 
        {
            "walltime": 18.803, 
            "slope": -0.037321, 
            "beta": 0, 
            "instance": 226
        }, 
        {
            "walltime": 5.871, 
            "slope": -0.038314, 
            "beta": 37, 
            "instance": 227
        }, 
        {
            "walltime": 5.067, 
            "slope": -0.039091, 
            "beta": 32, 
            "instance": 228
        }, 
        {
            "walltime": 8.199, 
            "slope": -0.03872, 
            "beta": 45, 
            "instance": 229
        }, 
        {
            "walltime": 7.277, 
            "slope": -0.038283, 
            "beta": 43, 
            "instance": 230
        }, 
        {
            "walltime": 6.571, 
            "slope": -0.037773, 
            "beta": 40, 
            "instance": 231
        }, 
        {
            "walltime": 6.594, 
            "slope": -0.038453, 
            "beta": 40, 
            "instance": 232
        }, 
        {
            "walltime": 6.472, 
            "slope": -0.037259, 
            "beta": 40, 
            "instance": 233
        }, 
        {
            "walltime": 9.488, 
            "slope": -0.038662, 
            "beta": 46, 
            "instance": 234
        }, 
        {
            "walltime": 4.845, 
            "slope": -0.039268, 
            "beta": 31, 
            "instance": 235
        }, 
        {
            "walltime": 6.755, 
            "slope": -0.038806, 
            "beta": 41, 
            "instance": 236
        }, 
        {
            "walltime": 4.85, 
            "slope": -0.040098, 
            "beta": 30, 
            "instance": 237
        }, 
        {
            "walltime": 6.693, 
            "slope": -0.038468, 
            "beta": 41, 
            "instance": 238
        }, 
        {
            "walltime": 13.005, 
            "slope": -0.03742, 
            "beta": 51, 
            "instance": 239
        }, 
        {
            "walltime": 6.614, 
            "slope": -0.038818, 
            "beta": 41, 
            "instance": 240
        }, 
        {
            "walltime": 5.961, 
            "slope": -0.038711, 
            "beta": 37, 
            "instance": 241
        }, 
        {
            "walltime": 17.93, 
            "slope": -0.037461, 
            "beta": 0, 
            "instance": 242
        }, 
        {
            "walltime": 13.353, 
            "slope": -0.03729, 
            "beta": 51, 
            "instance": 243
        }, 
        {
            "walltime": 4.331, 
            "slope": -0.041749, 
            "beta": 28, 
            "instance": 244
        }, 
        {
            "walltime": 6.804, 
            "slope": -0.038744, 
            "beta": 41, 
            "instance": 245
        }, 
        {
            "walltime": 6.879, 
            "slope": -0.03836, 
            "beta": 42, 
            "instance": 246
        }, 
        {
            "walltime": 13.017, 
            "slope": -0.036914, 
            "beta": 51, 
            "instance": 247
        }, 
        {
            "walltime": 6.394, 
            "slope": -0.038281, 
            "beta": 40, 
            "instance": 248
        }, 
        {
            "walltime": 3.65, 
            "slope": -0.04146, 
            "beta": 24, 
            "instance": 249
        }, 
        {
            "walltime": 18.564, 
            "slope": -0.037981, 
            "beta": 0, 
            "instance": 250
        }, 
        {
            "walltime": 3.638, 
            "slope": -0.041393, 
            "beta": 24, 
            "instance": 251
        }, 
        {
            "walltime": 6.276, 
            "slope": -0.038952, 
            "beta": 39, 
            "instance": 252
        }, 
        {
            "walltime": 7.1, 
            "slope": -0.039063, 
            "beta": 42, 
            "instance": 253
        }, 
        {
            "walltime": 7.243, 
            "slope": -0.03818, 
            "beta": 43, 
            "instance": 254
        }, 
        {
            "walltime": 8.353, 
            "slope": -0.037352, 
            "beta": 45, 
            "instance": 255
        }, 
        {
            "walltime": 6.135, 
            "slope": -0.037416, 
            "beta": 38, 
            "instance": 256
        }, 
        {
            "walltime": 5.542, 
            "slope": -0.038257, 
            "beta": 35, 
            "instance": 257
        }, 
        {
            "walltime": 9.515, 
            "slope": -0.037092, 
            "beta": 47, 
            "instance": 258
        }, 
        {
            "walltime": 5.839, 
            "slope": -0.038445, 
            "beta": 36, 
            "instance": 259
        }, 
        {
            "walltime": 9.683, 
            "slope": -0.038517, 
            "beta": 47, 
            "instance": 260
        }, 
        {
            "walltime": 6.79, 
            "slope": -0.038007, 
            "beta": 41, 
            "instance": 261
        }, 
        {
            "walltime": 18.885, 
            "slope": -0.036902, 
            "beta": 0, 
            "instance": 262
        }, 
        {
            "walltime": 5.127, 
            "slope": -0.038386, 
            "beta": 33, 
            "instance": 263
        }, 
        {
            "walltime": 6.477, 
            "slope": -0.039255, 
            "beta": 39, 
            "instance": 264
        }, 
        {
            "walltime": 6.453, 
            "slope": -0.038823, 
            "beta": 40, 
            "instance": 265
        }, 
        {
            "walltime": 8.782, 
            "slope": -0.03761, 
            "beta": 46, 
            "instance": 266
        }, 
        {
            "walltime": 2.536, 
            "slope": -0.042989, 
            "beta": 17, 
            "instance": 267
        }, 
        {
            "walltime": 7.162, 
            "slope": -0.038512, 
            "beta": 44, 
            "instance": 268
        }, 
        {
            "walltime": 5.85, 
            "slope": -0.038768, 
            "beta": 37, 
            "instance": 269
        }, 
        {
            "walltime": 6.262, 
            "slope": -0.038756, 
            "beta": 39, 
            "instance": 270
        }, 
        {
            "walltime": 5.326, 
            "slope": -0.037439, 
            "beta": 34, 
            "instance": 271
        }, 
        {
            "walltime": 5.766, 
            "slope": -0.038111, 
            "beta": 36, 
            "instance": 272
        }, 
        {
            "walltime": 4.336, 
            "slope": -0.039435, 
            "beta": 28, 
            "instance": 273
        }, 
        {
            "walltime": 5.269, 
            "slope": -0.038562, 
            "beta": 33, 
            "instance": 274
        }, 
        {
            "walltime": 7.141, 
            "slope": -0.0374, 
            "beta": 44, 
            "instance": 275
        }, 
        {
            "walltime": 6.704, 
            "slope": -0.038583, 
            "beta": 41, 
            "instance": 276
        }, 
        {
            "walltime": 5.302, 
            "slope": -0.038744, 
            "beta": 34, 
            "instance": 277
        }, 
        {
            "walltime": 17.572, 
            "slope": -0.036611, 
            "beta": 0, 
            "instance": 278
        }, 
        {
            "walltime": 6.678, 
            "slope": -0.038623, 
            "beta": 41, 
            "instance": 279
        }, 
        {
            "walltime": 5.713, 
            "slope": -0.03708, 
            "beta": 36, 
            "instance": 280
        }, 
        {
            "walltime": 6.808, 
            "slope": -0.038173, 
            "beta": 42, 
            "instance": 281
        }, 
        {
            "walltime": 6.735, 
            "slope": -0.03907, 
            "beta": 40, 
            "instance": 282
        }, 
        {
            "walltime": 5.495, 
            "slope": -0.03855, 
            "beta": 35, 
            "instance": 283
        }, 
        {
            "walltime": 5.277, 
            "slope": -0.039176, 
            "beta": 33, 
            "instance": 284
        }, 
        {
            "walltime": 8.729, 
            "slope": -0.038302, 
            "beta": 46, 
            "instance": 285
        }, 
        {
            "walltime": 5.915, 
            "slope": -0.038797, 
            "beta": 37, 
            "instance": 286
        }, 
        {
            "walltime": 18.668, 
            "slope": -0.037319, 
            "beta": 0, 
            "instance": 287
        }, 
        {
            "walltime": 4.629, 
            "slope": -0.04044, 
            "beta": 30, 
            "instance": 288
        }, 
        {
            "walltime": 6.358, 
            "slope": -0.038488, 
            "beta": 39, 
            "instance": 289
        }, 
        {
            "walltime": 6.686, 
            "slope": -0.03903, 
            "beta": 41, 
            "instance": 290
        }, 
        {
            "walltime": 10.373, 
            "slope": -0.038175, 
            "beta": 48, 
            "instance": 291
        }, 
        {
            "walltime": 4.33, 
            "slope": -0.041015, 
            "beta": 28, 
            "instance": 292
        }, 
        {
            "walltime": 4.929, 
            "slope": -0.039496, 
            "beta": 31, 
            "instance": 293
        }, 
        {
            "walltime": 4.96, 
            "slope": -0.039753, 
            "beta": 31, 
            "instance": 294
        }, 
        {
            "walltime": 5.027, 
            "slope": -0.039522, 
            "beta": 32, 
            "instance": 295
        }, 
        {
            "walltime": 6.009, 
            "slope": -0.040073, 
            "beta": 37, 
            "instance": 296
        }, 
        {
            "walltime": 7.146, 
            "slope": -0.038035, 
            "beta": 43, 
            "instance": 297
        }, 
        {
            "walltime": 11.242, 
            "slope": -0.037708, 
            "beta": 49, 
            "instance": 298
        }, 
        {
            "walltime": 16.831, 
            "slope": -0.036124, 
            "beta": 0, 
            "instance": 299
        }, 
        {
            "walltime": 5.578, 
            "slope": -0.038188, 
            "beta": 35, 
            "instance": 300
        }
    ], 
    "non_pruning_betas": "0", 
    "succ_running_time": 1890.287, 
    "reduction_strategy": "fpylll", 
    "pruning_betas": "2:80:1", 
    "avg_runtime_per_succ_problem": 6.824, 
    "problem_dimension": "56", 
    "lattice_version": "Schnorr"
}